LICENCE.txt
setup.py
srj_basic_calculator2.egg-info/PKG-INFO
srj_basic_calculator2.egg-info/SOURCES.txt
srj_basic_calculator2.egg-info/dependency_links.txt
srj_basic_calculator2.egg-info/top_level.txt
srjbasiccalc/__init__.py
srjbasiccalc/calc.py